stackit/authorization/__init__.py
stackit/authorization/api/__init__.py
stackit/authorization/api/default_api.py
stackit/authorization/api_client.py
stackit/authorization/api_response.py
stackit/authorization/configuration.py
stackit/authorization/exceptions.py
stackit/authorization/models/__init__.py
stackit/authorization/models/add_custom_role_response.py
stackit/authorization/models/add_members_payload.py
stackit/authorization/models/add_role_payload.py
stackit/authorization/models/assignable_subject.py
stackit/authorization/models/delete_role_response.py
stackit/authorization/models/error_response.py
stackit/authorization/models/existing_permission.py
stackit/authorization/models/get_role_response.py
stackit/authorization/models/list_assignable_subjects_response.py
stackit/authorization/models/list_members_response.py
stackit/authorization/models/list_permissions_response.py
stackit/authorization/models/list_user_memberships_response.py
stackit/authorization/models/list_user_permissions_response.py
stackit/authorization/models/member.py
stackit/authorization/models/members_response.py
stackit/authorization/models/permission.py
stackit/authorization/models/permission_request.py
stackit/authorization/models/remove_members_payload.py
stackit/authorization/models/role.py
stackit/authorization/models/roles_response.py
stackit/authorization/models/update_role_payload.py
stackit/authorization/models/update_role_response.py
stackit/authorization/models/user_membership.py
stackit/authorization/models/user_permission.py
stackit/authorization/models/zookie.py
stackit/authorization/py.typed
stackit/authorization/rest.py
stackit_authorization-0.6.0.dist-info/METADATA
stackit_authorization-0.6.0.dist-info/WHEEL
stackit_authorization-0.6.0.dist-info/licenses/LICENSE.md
stackit_authorization-0.6.0.dist-info/licenses/NOTICE.txt
stackit_authorization-0.6.0.dist-info/RECORD
